{
    "games": [
        {
            "title": "Wuthering Waves",
            "category": "gacha",
            "rank": "UR",
            "image": "https://cdn2.steamgriddb.com/grid/7cee9e13ee29834be975c2164736ad4d.png",
            "desc": "Wuthering Waves is a story-rich open-world action RPG with a high degree of freedom. You wake from your slumber as a Rover.",
            "tags": "Action RPG, Open World, Gacha, Post-Apocalyptic",
            "platform": "PC / Mobile / PS5",
            "dev": "Kuro Games",
            "meta_highlight": "LVL 55",
            "meta_sub": "DAILY // ACTIVE"
        },
        {
            "title": "Elden Ring",
            "category": "rpg",
            "rank": "UR",
            "image": "https://cdn2.steamgriddb.com/grid/a0abf0396a718b8982fce0b80181d8cb.png",
            "desc": "Rise, Tarnished, and be guided by grace to brandish the power of the Elden Ring and become an Elden Lord in the Lands Between.",
            "tags": "Soulslike, Dark Fantasy, Open World, RPG",
            "platform": "PC / Console",
            "dev": "FromSoftware",
            "meta_highlight": "120 HRS",
            "meta_sub": "COMPLETED"
        },
        {
            "title": "Cyberpunk 2077",
            "category": "rpg",
            "rank": "SSR",
            "image": "https://cdn2.steamgriddb.com/grid/4030e2eebb977639f8836aa25a293e40.png",
            "desc": "Cyberpunk 2077 is an open-world, action-adventure story set in Night City, a megalopolis obsessed with power and glamour.",
            "tags": "Cyberpunk, Shooter, Story Rich, Sci-Fi",
            "platform": "PC / Console",
            "dev": "CD Projekt Red",
            "meta_highlight": "★★★★",
            "meta_sub": "ARCHIVED"
        },
        {
            "title": "Valorant",
            "category": "gacha",
            "rank": "SSR",
            "image": "https://cdn2.steamgriddb.com/grid/276e4b3032ceaa7e52e9c0a41483d58f.png",
            "desc": "A 5v5 character-based tactical shooter where precise gunplay meets unique agent abilities.",
            "tags": "Shooter, Tactical, PvP, Competitive",
            "platform": "PC / Console",
            "dev": "Riot Games",
            "meta_highlight": "RANK: DIAMOND",
            "meta_sub": "ACTIVE"
        },
        {
            "title": "BioShock",
            "category": "rpg",
            "rank": "UR",
            "image": "https://cdn2.steamgriddb.com/grid/a265437321f8e7339486e92028a15101.png",
            "desc": "Explore the undersea city of Rapture, a haven for society's greatest minds that has devolved into a dystopian nightmare.",
            "tags": "FPS, Story Rich, Horror, Sci-Fi",
            "platform": "PC / Console",
            "dev": "Irrational Games",
            "meta_highlight": "★★★★★",
            "meta_sub": "CLASSIC"
        },
        {
            "title": "Tiny Bunny",
            "category": "rpg",
            "rank": "SSR",
            "image": "https://cdn2.steamgriddb.com/grid/e02d45699352e6f76d8344875084edc3.jpg",
            "desc": "A non-linear horror visual novel set in a quiet village lost in the Siberian forest. Be careful what you wish for.",
            "tags": "Horror, Visual Novel, Indie, Mystery",
            "platform": "PC",
            "dev": "Saikono",
            "meta_highlight": "EPISODE 4",
            "meta_sub": "READING"
        }
    ],
    "anime": [
        {
            "title": "Frieren",
            "category": "series",
            "rank": "UR",
            "image": "https://images3.alphacoders.com/132/1328972.jpeg",
            "desc": "Elf mage Frieren and her courageous fellow adventurers have defeated the Demon King and brought peace to the land.",
            "tags": "Fantasy, Slice of Life, Adventure, Drama",
            "platform": "TV Series",
            "dev": "Madhouse",
            "meta_highlight": "★★★★★",
            "meta_sub": "MASTERPIECE"
        },
        {
            "title": "Your Name",
            "category": "movie",
            "rank": "UR",
            "image": "https://images.alphacoders.com/846/846313.jpg",
            "desc": "Two strangers find themselves linked in a bizarre way. When a connection forms, will distance be the only thing to keep them apart?",
            "tags": "Romance, Drama, Supernatural",
            "platform": "Movie",
            "dev": "CoMix Wave Films",
            "meta_highlight": "★★★★★",
            "meta_sub": "REWATCHED"
        },
        {
            "title": "Edgerunners",
            "category": "series",
            "rank": "SSR",
            "image": "https://images4.alphacoders.com/937/937666.jpg",
            "desc": "A street kid tries to survive in a technology and body modification-obsessed city of the future.",
            "tags": "Cyberpunk, Sci-Fi, Action, Tragedy",
            "platform": "Netflix",
            "dev": "Studio Trigger",
            "meta_highlight": "★★★★",
            "meta_sub": "COMPLETED"
        }
    ]
}
